make_home_links/__init__.py
make_home_links/cli.py
make_home_links/install.py
make_home_links/log.py
make_home_links-0.1.0a1.dist-info/METADATA
make_home_links-0.1.0a1.dist-info/WHEEL
make_home_links-0.1.0a1.dist-info/entry_points.txt
make_home_links-0.1.0a1.dist-info/licenses/LICENSE
make_home_links-0.1.0a1.dist-info/RECORD
