Metadata-Version: 2.1
Name: make-home-links
Version: 0.1.0a1
Summary: Make symlinks to your home folder
Project-URL: Homepage, https://github.com/slavos1/make-home-links
Project-URL: Documentation, https://github.com/slavos1/make-home-links/README.md
Project-URL: Issues, https://github.com/slavos1/make-home-links/issues
Project-URL: Source, https://github.com/slavos1/make-home-links
Author-email: slavos1 <1396260+slavos1@users.noreply.github.com>
License: MIT
License-File: LICENSE
Keywords: cli,command line,command-line,tool
Classifier: Development Status :: 3 - Alpha
Classifier: Intended Audience :: Developers
Classifier: License :: OSI Approved :: MIT License
Classifier: Programming Language :: Python
Classifier: Programming Language :: Python :: 3.8
Classifier: Programming Language :: Python :: 3.9
Classifier: Programming Language :: Python :: 3.10
Classifier: Programming Language :: Python :: 3.11
Classifier: Programming Language :: Python :: 3.12
Classifier: Programming Language :: Python :: Implementation :: CPython
Classifier: Programming Language :: Python :: Implementation :: PyPy
Classifier: Topic :: Utilities
Requires-Python: >=3.8
Requires-Dist: loguru==0.7.2
Requires-Dist: tomli==2.0.1
